setup.py
line_enhancer/__init__.py
line_enhancer/line_enhancer.py
line_enhancer/maskstackcreator.py
line_enhancer.egg-info/PKG-INFO
line_enhancer.egg-info/SOURCES.txt
line_enhancer.egg-info/dependency_links.txt
line_enhancer.egg-info/entry_points.txt
line_enhancer.egg-info/requires.txt
line_enhancer.egg-info/top_level.txt