Metadata-Version: 1.0
Name: line-enhancer
Version: 1.0.0
Summary: Enhancing line images
Home-page: UNKNOWN
Author: Thorsten Wagner
Author-email: thorsten.wagner@mpi-dortmund.mpg.de
License: MIT
Platform: UNKNOWN
